{
  "entries": [
    {
      "date": "28 APR 2026",
      "verdict_line": "S&P 500 at all-time highs while US GDP prints 0.7% SAAR — the most expensive soft landing in history, and India's FIIs just blinked.",
      "themes": [
        "markets",
        "gdp_growth"
      ],
      "slugs": [
        "sp500",
        "nasdaq",
        "nikkei225",
        "euro_stoxx50",
        "bank_nifty"
      ]
    },
    {
      "date": "29 APR 2026",
      "verdict_line": "Airline passengers down 9% to a decade-low 35 million while GST prints ₹2 lakh crore — India's consumption story is splitting along a fault line the headline numbers hide.",
      "themes": [
        "consumption"
      ],
      "slugs": [
        "nikkei225",
        "sp500",
        "nasdaq",
        "euro_stoxx50",
        "us_vix",
        "airline_pax"
      ]
    },
    {
      "date": "30 APR 2026",
      "verdict_line": "Copper at a 10-year high of $5.94 while US GDP prints 0.7% SAAR — global demand signals are contradicting each other, and India's CAD is caught in the crossfire.",
      "themes": [
        "gdp_growth"
      ],
      "slugs": [
        "copper",
        "nikkei225",
        "sp500",
        "nasdaq",
        "euro_stoxx50"
      ]
    },
    {
      "date": "01 MAY 2026",
      "verdict_line": "Copper at an all-time high of $6.03 while India VIX jumps to 18.46 — industrial metals are pricing a boom that India's own volatility gauge refuses to believe.",
      "themes": [
        "markets"
      ],
      "slugs": [
        "copper",
        "nikkei225",
        "sp500",
        "nasdaq",
        "euro_stoxx50",
        "india_vix"
      ]
    },
    {
      "date": "02 MAY 2026",
      "verdict_line": "Nikkei at an all-time high of 59,513 while US GDP prints 0.7% SAAR — global equity is pricing a recovery that the world's largest economy has not yet delivered.",
      "themes": [
        "gdp_growth"
      ],
      "slugs": [
        "nikkei225",
        "euro_stoxx50",
        "us_10y_treasury",
        "nat_gas",
        "wti_usd"
      ]
    }
  ]
}